[{"_path":"/ru/models/svetlana","title":"Светлана","description":"Меня зовут Светлана. Я желаю познакомиться с достойным мужчиной. Люблю новые эмоции и открытия, поэтому легко завожу знакомства с новыми людьми, а VIP эскорт услуги для меня новая сфера, таким образом, я открываю для себя этот мир. Мы сможем красиво проводить время.\nЯ наделена великолепной утонченной фигурой и шикарной грудью. Хорошо воспитана, умею вести себя в деловом обществе, владею этикетом. Образование среднее специальное, но знаю несколько языков, поэтому ничто не станет преградой нашему общению.   Наше агентство вип эскорта поможет найти достойную твоего внимания девушку, приятную собеседницу и сногсшибательную сексуальную красотку. Только позвони. "},{"_path":"/ru/models/julia2","title":"Юлия","description":"Веселая, интересная девушка, элитная эскортница с обворожительной спортивной фигурой. Главное для меня – это приятные эмоции и красота. Эскорт – это мое хобби. Очень люблю встречи по вечерам, путешествовать и заводить новые знакомства с интересными мужчинами. Увлекаюсь художественной литературой. \nИзучаю французский язык. Высшего образования у меня нет, но легко нахожу общий язык с людьми из разных обществ. В нашем агентстве дорогие эскорт услуги, и мои не исключение. Для того, чтобы организовать встречу со мной, свяжитесь с нашим менеджером."}]