[{"_path":"/ru/models/liana","title":"Лиана","description":"Я жгучая брюнетка с роскошным смуглым телом, голубыми глазами, которая предоставляет vip эскорт услуги. Со мной у вас будет незабываемый отдых и по настоящему сладкое удовольствие. Предпочитаю общение с успешными и уверенными в себе мужчинами. Изучаю итальянский и английский языки, последним владею в совершенстве, могу свободно общаться с иностранцами. \nУ меня есть высшее образование, умею вести беседы в элитном обществе. Если хотите встретиться со мной, свяжитесь с нашим агентством вип эскорта и наш менеджер организует нам незабываемую встречу."},{"_path":"/ru/models/nika2","title":"Ника","description":"Роскошная девушка с широкими бедрами, голливудской улыбкой и обворожительными зелеными глазами. Я элитная эскортница, которая принесет вам незабываемое удовольствие. Люблю проводить время за ужином в ресторане, а потом продолжить вечер в шикарном номере отеля. Мое хобби – это рисование хной на теле. Предпочитаю общение с красивыми и уверенными в себе мужчинами. Изучаю испанский язык, английский  и увлекаюсь романами.\nЕсли вам интересны дорогие эскорт услуги, то обращайтесь в наше агентство и наш менеджер организует вам vip отдых со мной."}]