[{"_path":"/models/louise","title":"Louise","description":"I'm sure you haven't seen a body as thin as mine before.  A gorgeous smile and figure helped me to master modeling and get an excellent experience in this business. I am a nice girl who is into different sciences (like astronomy), and reading scientific books, so you will have something to talk to me about. I have a higher education, I know several foreign languages among which are English, and Spanish. Suitable for escorting models at VIP events, help me to forget about loneliness during a holiday at a hotel or dinner at a restaurant. \nHave you been looking for a beautiful escort girl for a long time?  Hurry up and write to our manager and he will organize a meeting!"},{"_path":"/models/asya","title":"Asya","description":"I am a maddeningly charming, burning blonde, who provides luxury escort services to men and will not make you bored in the evenings. My incredible figure and model look attract decent men. \nWith me you'll forget about the amazing boredom because I offer VIP escort at various events; I'll gladly keep you company at a private party, during a dinner at a restaurant, or on a vacation in a hotel. My heart is filled with love for escorts and travels to wonderful warm countries. I also have a college degree and know several foreign languages. Contact our manager and we will meet soon!"}]