[{"_path":"/models/lily","title":"Lily","description":"Hot blonde with a trim figure and gorgeous forms is always ready to decorate your evening. I am a VIP escort and work as a model in magazines, which is why my main hobbies are photo sessions, traveling, and shopping. I love to spend time with interesting and successful men and give them joy and pleasure during their leisure. I will gladly accompany you at events, in restaurants, while sailing on yachts. We can also have privacy in a hotel room, order a bottle of wine, and relax in an intimate setting. \nTo order a meeting with me, contact the agency VIP escort, and the manager will organize an unforgettable vacation together."},{"_path":"/models/ely","title":"Ely","description":"A girl with long hair and a very sexy appearance. My glamorous image, erudition and sensual character attract at first sight. I am fond of club dancing, psychology. I participate in various photo and video shoots. I like to meet and relax beautifully with successful men. Despite the image of a glamorous beauty, I can give you my affection and care."}]